CHANGES.txt
LICENSE.txt
README.txt
setup.py
src/PloneFolderContentsTopBottomLinks/__init__.py
src/PloneFolderContentsTopBottomLinks/configure.zcml
src/PloneFolderContentsTopBottomLinks/patch.py
src/PloneFolderContentsTopBottomLinks/table.pt
src/PloneFolderContentsTopBottomLinks.egg-info/PKG-INFO
src/PloneFolderContentsTopBottomLinks.egg-info/SOURCES.txt
src/PloneFolderContentsTopBottomLinks.egg-info/dependency_links.txt
src/PloneFolderContentsTopBottomLinks.egg-info/entry_points.txt
src/PloneFolderContentsTopBottomLinks.egg-info/not-zip-safe
src/PloneFolderContentsTopBottomLinks.egg-info/requires.txt
src/PloneFolderContentsTopBottomLinks.egg-info/top_level.txt