Metadata-Version: 1.0
Name: PloneFolderContentsTopBottomLinks
Version: 2.0
Summary: Patch folder contents to show top and bottom links (Plone 4 compatible release)
Home-page: http://pypi.python.org/pypi/PloneFolderContentsTopBottomLinks
Author: Laurence Rowe
Author-email: plone-developers@lists.sourceforge.net
License: GPL
Keywords: plone content views viewlet
Platform: UNKNOWN
Classifier: Framework :: Plone
Classifier: License :: OSI Approved :: GNU General Public License (GPL)
Classifier: Programming Language :: Python
